colcon_runner/__init__.py
colcon_runner/colcon_runner.py
colcon_runner-0.8.1.dist-info/METADATA
colcon_runner-0.8.1.dist-info/WHEEL
colcon_runner-0.8.1.dist-info/entry_points.txt
colcon_runner-0.8.1.dist-info/licenses/LICENSE
colcon_runner-0.8.1.dist-info/RECORD
