Metadata-Version: 2.4
Name: colcon-runner
Version: 0.8.1
Summary: A concise CLI wrapper for colcon build/test/clean workflows.
Project-URL: Source, https://github.com/blooop/colcon_runner
Project-URL: Home, https://github.com/blooop/colcon_runner
Author-email: Austin Gregg-Smith <blooop@gmail.com>
License-Expression: MIT
License-File: LICENSE
Provides-Extra: test
Requires-Dist: coverage<=7.13.1,>=7.5.4; extra == 'test'
Requires-Dist: hypothesis<=6.148.9,>=6.104.2; extra == 'test'
Requires-Dist: pre-commit==4.5.1; extra == 'test'
Requires-Dist: pylint<=4.0.4,>=3.2.5; extra == 'test'
Requires-Dist: pytest-cov<=7.0.0,>=4.1; extra == 'test'
Requires-Dist: pytest<=9.0.2,>=7.4; extra == 'test'
Requires-Dist: ruff<=0.14.10,>=0.5.0; extra == 'test'
Requires-Dist: ty>=0.0.8; extra == 'test'
